hurlers/__init__.py
hurlers/atbat.py
hurlers/game.py
hurlers/inning.py
hurlers/pitch.py
hurlers/player.py
hurlers/runner.py
hurlers/tests/__init__.py
hurlers/tests/atbat_test.py
hurlers/tests/game_test.py
hurlers/tests/inning_test.py
hurlers/tests/runner_test.py
hurlers/tests/server_fixture.py
hurlers/utils/__init__.py
hurlers/utils/constants.py
hurlers/utils/csv_utils.py
hurlers/utils/soup_utils.py
hurlers/utils/url_utils.py
hurlers-0.1.1.dist-info/METADATA
hurlers-0.1.1.dist-info/WHEEL
hurlers-0.1.1.dist-info/top_level.txt
hurlers-0.1.1.dist-info/RECORD
